jira_agile_toolbox/__init__.py
jira_agile_toolbox/_version.py
jira_agile_toolbox-0.0.15.dist-info/METADATA
jira_agile_toolbox-0.0.15.dist-info/WHEEL
jira_agile_toolbox-0.0.15.dist-info/licenses/LICENSE
jira_agile_toolbox-0.0.15.dist-info/RECORD
