Metadata-Version: 2.4
Name: jira_agile_toolbox
Version: 0.0.15
Summary: Extends standard jira package with agile specific tooling for metrics and administration
Project-URL: Homepage, https://github.com/studioj/jira-agile-toolbox
Project-URL: Documentation, https://jira-agile-toolbox.readthedocs.io/
Project-URL: Repository, https://github.com/studioj/jira-agile-toolbox.git
Author-email: Jef Neefs <noreply@gmail.com>
License: MIT
License-File: LICENSE
Keywords: agile,api,atlassian,jira,kanban,rest,scrum,web
Classifier: Development Status :: 1 - Planning
Classifier: Intended Audience :: Developers
Classifier: Intended Audience :: Information Technology
Classifier: License :: OSI Approved :: MIT License
Classifier: Operating System :: MacOS :: MacOS X
Classifier: Operating System :: Microsoft :: Windows
Classifier: Operating System :: OS Independent
Classifier: Operating System :: POSIX
Classifier: Programming Language :: Python :: 3
Classifier: Programming Language :: Python :: 3 :: Only
Classifier: Programming Language :: Python :: 3.9
Classifier: Programming Language :: Python :: 3.10
Classifier: Programming Language :: Python :: 3.11
Classifier: Programming Language :: Python :: 3.12
Classifier: Programming Language :: Python :: 3.13
Classifier: Topic :: Internet :: WWW/HTTP
Classifier: Topic :: Office/Business
Classifier: Topic :: Software Development
Classifier: Topic :: Software Development :: Libraries
Classifier: Topic :: Software Development :: Libraries :: Python Modules
Classifier: Topic :: Software Development :: Testing
Classifier: Topic :: Utilities
Requires-Python: >=3.6
Requires-Dist: jira
